kenjyco_libs/__init__.py
kenjyco_libs/settings.ini
kenjyco_libs/scripts/__init__.py
kenjyco_libs/scripts/dev_setup.py
kenjyco_libs/scripts/shell.py
kenjyco_libs-0.0.11.dist-info/LICENSE.txt
kenjyco_libs-0.0.11.dist-info/METADATA
kenjyco_libs-0.0.11.dist-info/WHEEL
kenjyco_libs-0.0.11.dist-info/entry_points.txt
kenjyco_libs-0.0.11.dist-info/top_level.txt
kenjyco_libs-0.0.11.dist-info/RECORD
