Metadata-Version: 2.1
Name: kenjyco-libs
Version: 0.0.11
Summary: Easily install kenjyco libs
Home-page: https://github.com/kenjyco/kenjyco-libs
Download-URL: https://github.com/kenjyco/kenjyco-libs/tarball/v0.0.11
Author: Ken
Author-email: kenjyco@gmail.com
License: MIT
Keywords: api,data,libs,cli,meta-package,command-line,helper,kenjyco
Classifier: Development Status :: 4 - Beta
Classifier: Environment :: Console
Classifier: Intended Audience :: Developers
Classifier: License :: OSI Approved :: MIT License
Classifier: Operating System :: MacOS :: MacOS X
Classifier: Operating System :: POSIX :: Linux
Classifier: Programming Language :: Python :: 3.5
Classifier: Programming Language :: Python :: 3.6
Classifier: Programming Language :: Python :: 3.7
Classifier: Programming Language :: Python :: 3.8
Classifier: Programming Language :: Python :: 3.9
Classifier: Programming Language :: Python :: 3.10
Classifier: Programming Language :: Python :: 3.11
Classifier: Programming Language :: Python :: 3.12
Classifier: Programming Language :: Python :: 3.13
Classifier: Programming Language :: Python
Classifier: Topic :: Software Development :: Libraries
Classifier: Topic :: Utilities
License-File: LICENSE.txt
Requires-Dist: bg-helper
Requires-Dist: click (>=6.0)
Requires-Dist: fs-helper
Requires-Dist: input-helper
Requires-Dist: settings-helper
Provides-Extra: bs4
Requires-Dist: beautifulsoup4 ; extra == 'bs4'
Requires-Dist: lxml ; extra == 'bs4'
Provides-Extra: data
Requires-Dist: aws-info-helper ; extra == 'data'
Requires-Dist: dt-helper ; extra == 'data'
Requires-Dist: webclient-helper ; extra == 'data'
Requires-Dist: sql-helper ; extra == 'data'
Requires-Dist: chloop ; extra == 'data'
Requires-Dist: mongo-helper ; extra == 'data'
Requires-Dist: redis-helper ; extra == 'data'
Requires-Dist: xmljson ; extra == 'data'
Requires-Dist: expectation-helper ; (python_version >= "3.8") and extra == 'data'
Provides-Extra: dev
Requires-Dist: readme-helper ; extra == 'dev'
Requires-Dist: testing-helper ; extra == 'dev'
Provides-Extra: full
Requires-Dist: beautifulsoup4 ; extra == 'full'
Requires-Dist: lxml ; extra == 'full'
Requires-Dist: aws-info-helper ; extra == 'full'
Requires-Dist: dt-helper ; extra == 'full'
Requires-Dist: webclient-helper ; extra == 'full'
Requires-Dist: sql-helper ; extra == 'full'
Requires-Dist: chloop ; extra == 'full'
Requires-Dist: mongo-helper ; extra == 'full'
Requires-Dist: redis-helper ; extra == 'full'
Requires-Dist: xmljson ; extra == 'full'
Requires-Dist: readme-helper ; extra == 'full'
Requires-Dist: testing-helper ; extra == 'full'
Requires-Dist: ipython ; extra == 'full'
Requires-Dist: expectation-helper ; (python_version >= "3.8") and extra == 'full'
Provides-Extra: ipython
Requires-Dist: ipython ; extra == 'ipython'
Provides-Extra: nosql
Requires-Dist: chloop ; extra == 'nosql'
Requires-Dist: mongo-helper ; extra == 'nosql'
Requires-Dist: redis-helper ; extra == 'nosql'
Provides-Extra: sql
Requires-Dist: sql-helper ; extra == 'sql'
Requires-Dist: expectation-helper ; (python_version >= "3.8") and extra == 'sql'
Provides-Extra: xmljson
Requires-Dist: xmljson ; extra == 'xmljson'
